ai_ffmpeg_cli/__init__.py
ai_ffmpeg_cli/ascii_art.py
ai_ffmpeg_cli/command_builder.py
ai_ffmpeg_cli/config.py
ai_ffmpeg_cli/confirm.py
ai_ffmpeg_cli/context_scanner_basic.py
ai_ffmpeg_cli/context_scanner_extended.py
ai_ffmpeg_cli/credential_security.py
ai_ffmpeg_cli/custom_exceptions.py
ai_ffmpeg_cli/executor.py
ai_ffmpeg_cli/file_operations.py
ai_ffmpeg_cli/intent_models.py
ai_ffmpeg_cli/intent_models_extended.py
ai_ffmpeg_cli/intent_router.py
ai_ffmpeg_cli/llm_client.py
ai_ffmpeg_cli/main.py
ai_ffmpeg_cli/path_security.py
ai_ffmpeg_cli/prompt_enhancer.py
ai_ffmpeg_cli/token_tracker.py
ai_ffmpeg_cli/user_prompts.py
ai_ffmpeg_cli/version_info.py
ai_ffmpeg_cli/logging_config/__init__.py
ai_ffmpeg_cli/logging_config/config.py
ai_ffmpeg_cli/logging_config/context.py
ai_ffmpeg_cli-0.2.6.dist-info/METADATA
ai_ffmpeg_cli-0.2.6.dist-info/WHEEL
ai_ffmpeg_cli-0.2.6.dist-info/entry_points.txt
ai_ffmpeg_cli-0.2.6.dist-info/licenses/LICENSE
ai_ffmpeg_cli-0.2.6.dist-info/RECORD
