Metadata-Version: 2.4
Name: ai-ffmpeg-cli
Version: 0.2.6
Summary: AI-powered CLI that translates natural language to safe ffmpeg commands
Project-URL: Homepage, https://github.com/d-k-patel/ai-ffmpeg-cli
Project-URL: Documentation, https://d-k-patel.github.io/ai-ffmpeg-cli/
Project-URL: Repository, https://github.com/d-k-patel/ai-ffmpeg-cli
Project-URL: Bug Tracker, https://github.com/d-k-patel/ai-ffmpeg-cli/issues
Project-URL: Discussions, https://github.com/d-k-patel/ai-ffmpeg-cli/discussions
Project-URL: Changelog, https://github.com/d-k-patel/ai-ffmpeg-cli/releases
Project-URL: Funding, https://github.com/sponsors/d-k-patel
Author-email: thedkpatel <dhruv@thedkpatel.com>
Maintainer-email: thedkpatel <dhruv@thedkpatel.com>
License: MIT License
License-File: LICENSE
Keywords: ai,audio,automation,cli,conversion,ffmpeg,media-processing,natural-language,video
Classifier: Development Status :: 4 - Beta
Classifier: Environment :: Console
Classifier: Intended Audience :: Developers
Classifier: Intended Audience :: End Users/Desktop
Classifier: License :: OSI Approved :: MIT License
Classifier: Operating System :: OS Independent
Classifier: Programming Language :: Python :: 3
Classifier: Programming Language :: Python :: 3 :: Only
Classifier: Programming Language :: Python :: 3.10
Classifier: Programming Language :: Python :: 3.11
Classifier: Programming Language :: Python :: 3.12
Classifier: Programming Language :: Python :: 3.13
Classifier: Topic :: Multimedia :: Video
Classifier: Topic :: Multimedia :: Video :: Conversion
Classifier: Topic :: Software Development :: Libraries :: Python Modules
Classifier: Topic :: System :: System Shells
Classifier: Topic :: Utilities
Requires-Python: >=3.10
Requires-Dist: openai>=1.37.0
Requires-Dist: pydantic>=2.0.0
Requires-Dist: pyfiglet>=1.0.0
Requires-Dist: python-dotenv>=1.0.0
Requires-Dist: rich>=13.0.0
Requires-Dist: tiktoken>=0.5.0
Requires-Dist: typer>=0.9.0
Requires-Dist: typing-extensions>=4.8.0
Provides-Extra: all
Requires-Dist: mkdocs-material>=9.0.0; extra == 'all'
Requires-Dist: mkdocs-mermaid2-plugin>=1.0.0; extra == 'all'
Requires-Dist: mkdocs>=1.5.0; extra == 'all'
Requires-Dist: mypy>=1.5.0; extra == 'all'
Requires-Dist: pre-commit>=3.0.0; extra == 'all'
Requires-Dist: psutil>=5.0.0; extra == 'all'
Requires-Dist: pytest-cov>=6.0.0; extra == 'all'
Requires-Dist: pytest-mock>=3.10.0; extra == 'all'
Requires-Dist: pytest>=7.0.0; extra == 'all'
Requires-Dist: ruff>=0.5.0; extra == 'all'
Provides-Extra: dev
Requires-Dist: mypy>=1.5.0; extra == 'dev'
Requires-Dist: pre-commit>=3.0.0; extra == 'dev'
Requires-Dist: psutil>=5.0.0; extra == 'dev'
Requires-Dist: pytest-cov>=6.0.0; extra == 'dev'
Requires-Dist: pytest-mock>=3.10.0; extra == 'dev'
Requires-Dist: pytest>=7.0.0; extra == 'dev'
Requires-Dist: ruff>=0.5.0; extra == 'dev'
Provides-Extra: docs
Requires-Dist: mkdocs-material>=9.0.0; extra == 'docs'
Requires-Dist: mkdocs-mermaid2-plugin>=1.0.0; extra == 'docs'
Requires-Dist: mkdocs>=1.5.0; extra == 'docs'
Provides-Extra: test
Requires-Dist: psutil>=5.0.0; extra == 'test'
Requires-Dist: pytest-cov>=4.0.0; extra == 'test'
Requires-Dist: pytest-mock>=3.10.0; extra == 'test'
Requires-Dist: pytest>=7.0.0; extra == 'test'
